jdAppStreamEdit/AboutWindow.py
jdAppStreamEdit/AdvancedWidget.py
jdAppStreamEdit/ArtifactWindow.py
jdAppStreamEdit/ChangelogImporter.py
jdAppStreamEdit/ComposeDirectoryWindow.py
jdAppStreamEdit/Constants.py
jdAppStreamEdit/DescriptionWidget.py
jdAppStreamEdit/Environment.py
jdAppStreamEdit/ExternalReleasesWindow.py
jdAppStreamEdit/Functions.py
jdAppStreamEdit/Icon.svg
jdAppStreamEdit/ImportChangelogWindow.py
jdAppStreamEdit/Interfaces.py
jdAppStreamEdit/Languages.py
jdAppStreamEdit/MainWindow.py
jdAppStreamEdit/ManageTemplatesWindow.py
jdAppStreamEdit/OarsWidget.py
jdAppStreamEdit/PluginAPI.py
jdAppStreamEdit/PluginLoader.py
jdAppStreamEdit/PluginWindow.py
jdAppStreamEdit/RelationsWidget.py
jdAppStreamEdit/ReleaseImporter.py
jdAppStreamEdit/ReleasesWidget.py
jdAppStreamEdit/ReleasesWindow.py
jdAppStreamEdit/ScreenshotWindow.py
jdAppStreamEdit/Settings.py
jdAppStreamEdit/SettingsWindow.py
jdAppStreamEdit/SysinfoWindow.py
jdAppStreamEdit/ThumbnailWindow.py
jdAppStreamEdit/TranslateWindow.py
jdAppStreamEdit/Types.py
jdAppStreamEdit/ValidateWindow.py
jdAppStreamEdit/ViewCatalogWindow.py
jdAppStreamEdit/ViewXMLWindow.py
jdAppStreamEdit/XMLHighlighter.py
jdAppStreamEdit/__init__.py
jdAppStreamEdit/__main__.py
jdAppStreamEdit/version.txt
jdAppStreamEdit/data/categories.txt
jdAppStreamEdit/data/changelog.html
jdAppStreamEdit/data/language_codes.csv
jdAppStreamEdit/data/metadata_licenses.json
jdAppStreamEdit/data/platform.json
jdAppStreamEdit/data/project_licenses.json
jdAppStreamEdit/data/translators.json
jdAppStreamEdit/translations/jdAppStreamEdit_de.qm
jdAppStreamEdit/translations/jdAppStreamEdit_nl.qm
jdAppStreamEdit/translations/jdAppStreamEdit_ru.qm
jdAppStreamEdit/ui_compiled/AboutWindow.py
jdAppStreamEdit/ui_compiled/AdvancedWidget.py
jdAppStreamEdit/ui_compiled/ArtifactWindow.py
jdAppStreamEdit/ui_compiled/ComposeDirectoryWindow.py
jdAppStreamEdit/ui_compiled/DescriptionWidget.py
jdAppStreamEdit/ui_compiled/ExternalReleasesWindow.py
jdAppStreamEdit-9.2.dist-info/LICENSE
jdAppStreamEdit-9.2.dist-info/METADATA
jdAppStreamEdit-9.2.dist-info/WHEEL
jdAppStreamEdit-9.2.dist-info/entry_points.txt
jdAppStreamEdit-9.2.dist-info/top_level.txt
jdAppStreamEdit-9.2.dist-info/RECORD
