Metadata-Version: 2.1
Name: jdAppStreamEdit
Version: 9.2
Summary: A graphical Program to create and edit AppStream files
Author-email: JakobDev <jakobdev@gmx.de>
License: GPL-3
Project-URL: Source, https://codeberg.org/JakobDev/jdAppStreamEdit
Project-URL: Issues, https://codeberg.org/JakobDev/jdAppStreamEdit/issues
Project-URL: Translate, https://translate.codeberg.org/projects/jdAppStreamEdit
Project-URL: Donation, https://ko-fi.com/jakobdev
Keywords: JakobDev,Linux,Freedesktop,AppStream
Classifier: Development Status :: 5 - Production/Stable
Classifier: Intended Audience :: Developers
Classifier: Environment :: X11 Applications :: Qt
Classifier: License :: OSI Approved :: GNU General Public License v3 (GPLv3)
Classifier: Natural Language :: English
Classifier: Natural Language :: German
Classifier: Natural Language :: Dutch
Classifier: Operating System :: OS Independent
Classifier: Operating System :: POSIX
Classifier: Operating System :: POSIX :: BSD
Classifier: Operating System :: POSIX :: Linux
Classifier: Operating System :: MacOS :: MacOS X
Classifier: Operating System :: Microsoft :: Windows
Classifier: Programming Language :: Python :: 3
Classifier: Programming Language :: Python :: 3.9
Classifier: Programming Language :: Python :: 3.10
Classifier: Programming Language :: Python :: 3.11
Classifier: Programming Language :: Python :: 3 :: Only
Classifier: Programming Language :: Python :: Implementation :: CPython
Requires-Python: >=3.9
License-File: LICENSE
Requires-Dist: PyQt6
Requires-Dist: requests
Requires-Dist: lxml
Provides-Extra: import-desktop-files
Requires-Dist: desktop-entry-lib; extra == "import-desktop-files"
Provides-Extra: sort-releases
Requires-Dist: packaging; extra == "sort-releases"
Provides-Extra: use-editorconfig
Requires-Dist: editorconfig; extra == "use-editorconfig"
